testionary/__init__.py
testionary/py.typed
testionary/tracking_dict.py
testionary-0.2.0.dist-info/WHEEL
testionary-0.2.0.dist-info/METADATA
testionary-0.2.0.dist-info/RECORD
